{"nodes": [{"id": "c_users_lishuai_desktop_oaiss_chain_test_screenshots_nav_page_py", "label": "nav_page.py", "file_type": "code", "source_file": "C:\\Users\\LiShuai\\Desktop\\OAISS CHAIN\\test-screenshots\\nav_page.py", "source_location": "L1"}], "edges": [{"source": "c_users_lishuai_desktop_oaiss_chain_test_screenshots_nav_page_py", "target": "json", "relation": "imports", "context": "import", "confidence": "EXTRACTED", "source_file": "C:\\Users\\LiShuai\\Desktop\\OAISS CHAIN\\test-screenshots\\nav_page.py", "source_location": "L1", "weight": 1.0}, {"source": "c_users_lishuai_desktop_oaiss_chain_test_screenshots_nav_page_py", "target": "time", "relation": "imports", "context": "import", "confidence": "EXTRACTED", "source_file": "C:\\Users\\LiShuai\\Desktop\\OAISS CHAIN\\test-screenshots\\nav_page.py", "source_location": "L1", "weight": 1.0}, {"source": "c_users_lishuai_desktop_oaiss_chain_test_screenshots_nav_page_py", "target": "subprocess", "relation": "imports", "context": "import", "confidence": "EXTRACTED", "source_file": "C:\\Users\\LiShuai\\Desktop\\OAISS CHAIN\\test-screenshots\\nav_page.py", "source_location": "L1", "weight": 1.0}, {"source": "c_users_lishuai_desktop_oaiss_chain_test_screenshots_nav_page_py", "target": "sys", "relation": "imports", "context": "import", "confidence": "EXTRACTED", "source_file": "C:\\Users\\LiShuai\\Desktop\\OAISS CHAIN\\test-screenshots\\nav_page.py", "source_location": "L1", "weight": 1.0}], "raw_calls": []}